{"id":"VariableCollectionId:441:2012","name":"Effect","modes":{"441:0":"Mode 1"},"variableIds":["VariableID:441:2056","VariableID:441:2049","VariableID:441:2050","VariableID:441:2051","VariableID:441:2052","VariableID:441:2053","VariableID:441:2058","VariableID:438:11136","VariableID:438:11137","VariableID:438:11138","VariableID:438:11139","VariableID:438:11140"],"variables":[{"id":"VariableID:441:2049","name":"Shadow_Thick/Position-X","description":"","type":"FLOAT","valuesByMode":{"441:0":1},"resolvedValuesByMode":{"441:0":{"resolvedValue":1,"alias":null}},"scopes":["ALL_SCOPES"],"hiddenFromPublishing":false,"codeSyntax":{}},{"id":"VariableID:441:2050","name":"Shadow_Thick/Position-Y","description":"","type":"FLOAT","valuesByMode":{"441:0":6},"resolvedValuesByMode":{"441:0":{"resolvedValue":6,"alias":null}},"scopes":["ALL_SCOPES"],"hiddenFromPublishing":false,"codeSyntax":{}},{"id":"VariableID:441:2051","name":"Shadow_Thick/Blur","description":"","type":"FLOAT","valuesByMode":{"441:0":20},"resolvedValuesByMode":{"441:0":{"resolvedValue":20,"alias":null}},"scopes":["ALL_SCOPES"],"hiddenFromPublishing":false,"codeSyntax":{}},{"id":"VariableID:441:2052","name":"Shadow_Thick/Spread","description":"","type":"FLOAT","valuesByMode":{"441:0":0},"resolvedValuesByMode":{"441:0":{"resolvedValue":0,"alias":null}},"scopes":["ALL_SCOPES"],"hiddenFromPublishing":false,"codeSyntax":{}},{"id":"VariableID:441:2053","name":"Shadow_Thick/Color","description":"","type":"COLOR","valuesByMode":{"441:0":{"type":"VARIABLE_ALIAS","id":"VariableID:438:11135"}},"resolvedValuesByMode":{"441:0":{"resolvedValue":{"r":0,"g":0,"b":0,"a":0.10000000149011612},"alias":"VariableID:438:11135","aliasName":"Color/B&W/Shadow"}},"scopes":["ALL_SCOPES"],"hiddenFromPublishing":false,"codeSyntax":{}},{"id":"VariableID:438:11136","name":"Shadow_Thin/Position-X","description":"","type":"FLOAT","valuesByMode":{"441:0":1},"resolvedValuesByMode":{"441:0":{"resolvedValue":1,"alias":null}},"scopes":["ALL_SCOPES"],"hiddenFromPublishing":false,"codeSyntax":{}},{"id":"VariableID:438:11137","name":"Shadow_Thin/Position-Y","description":"","type":"FLOAT","valuesByMode":{"441:0":3},"resolvedValuesByMode":{"441:0":{"resolvedValue":3,"alias":null}},"scopes":["ALL_SCOPES"],"hiddenFromPublishing":false,"codeSyntax":{}},{"id":"VariableID:438:11138","name":"Shadow_Thin/Blur","description":"","type":"FLOAT","valuesByMode":{"441:0":8},"resolvedValuesByMode":{"441:0":{"resolvedValue":8,"alias":null}},"scopes":["ALL_SCOPES"],"hiddenFromPublishing":false,"codeSyntax":{}},{"id":"VariableID:438:11139","name":"Shadow_Thin/Spread","description":"","type":"FLOAT","valuesByMode":{"441:0":0},"resolvedValuesByMode":{"441:0":{"resolvedValue":0,"alias":null}},"scopes":["ALL_SCOPES"],"hiddenFromPublishing":false,"codeSyntax":{}},{"id":"VariableID:438:11140","name":"Shadow_Thin/Color","description":"","type":"COLOR","valuesByMode":{"441:0":{"type":"VARIABLE_ALIAS","id":"VariableID:438:11135"}},"resolvedValuesByMode":{"441:0":{"resolvedValue":{"r":0,"g":0,"b":0,"a":0.10000000149011612},"alias":"VariableID:438:11135","aliasName":"Color/B&W/Shadow"}},"scopes":["ALL_SCOPES"],"hiddenFromPublishing":false,"codeSyntax":{}},{"id":"VariableID:441:2056","name":"Shadow_Thick/Name","description":"","type":"STRING","valuesByMode":{"441:0":"Shadow_Thick"},"resolvedValuesByMode":{"441:0":{"resolvedValue":"Shadow_Thick","alias":null}},"scopes":["ALL_SCOPES"],"hiddenFromPublishing":false,"codeSyntax":{}},{"id":"VariableID:441:2058","name":"Shadow_Thin/Name","description":"","type":"STRING","valuesByMode":{"441:0":"Shadow_Thin"},"resolvedValuesByMode":{"441:0":{"resolvedValue":"Shadow_Thin","alias":null}},"scopes":["ALL_SCOPES"],"hiddenFromPublishing":false,"codeSyntax":{}}]}